svgbit/__init__.py
svgbit/__main__.py
svgbit/filters.py
svgbit/normalizers.py
svgbit/plot.py
svgbit/run.py
svgbit/core/STDataset.py
svgbit/core/__init__.py
svgbit/core/cluster.py
svgbit/core/combinations.py
svgbit/core/density.py
svgbit/core/filters.py
svgbit/core/io.py
svgbit/core/moran.py
svgbit/core/normalizers.py
svgbit/core/plot.py
svgbit/core/utils.py
svgbit-0.2.17.dist-info/LICENSE
svgbit-0.2.17.dist-info/METADATA
svgbit-0.2.17.dist-info/WHEEL
svgbit-0.2.17.dist-info/entry_points.txt
svgbit-0.2.17.dist-info/top_level.txt
svgbit-0.2.17.dist-info/RECORD
