Metadata-Version: 2.1
Name: svgbit
Version: 0.2.17
Summary: Find spatial variable genes for Spatial Trasncriptomics data.
Author-email: CPenglab <chengpeng@ynu.edu.cn>
License: GPLv3
Project-URL: documentation, https://svgbit.readthedocs.io
Project-URL: repository, https://github.com/CPenglab/svgbit
Classifier: Development Status :: 4 - Beta
Classifier: Environment :: Console
Classifier: License :: OSI Approved :: GNU General Public License v3 (GPLv3)
Classifier: Operating System :: OS Independent
Classifier: Programming Language :: Python :: 3 :: Only
Classifier: Programming Language :: Python :: Implementation :: CPython
Classifier: Topic :: Scientific/Engineering :: Bio-Informatics
Requires-Python: >=3.8
License-File: LICENSE
Requires-Dist: anndata >=0.8.0
Requires-Dist: matplotlib >=3.5.1
Requires-Dist: pysal >=2.4.0
Requires-Dist: pillow >=9.2.0
